{
  "postNo": "261811",
  "researchPeriod": {
    "totalText": "'26.4.~'31.12. (5년 9개월)",
    "totalMonths": 69,
    "byStageText": "총 연구기간 2026.4.~2031.12.(3+3년); 1~6차년도 각 12개월(1차년도는 2026.4.~2026.12 9개월)",
    "firstYearText": "'26.4.~'26.12. (9개월)"
  },
  "funding": {
    "perYearPerProjectText": "과제당 연 12억원(1~6차년도 각 12억원)",
    "totalScaleText": "총 72억원('26년 12억원)",
    "numAwardsText": "1개 과제"
  },
  "eligibility": {
    "employmentType": "무관/해당없음",
    "employmentEvidence": "연구책임자의 자격 -「국가연구개발혁신법」제2조제3호에서 정하는 기관 및 단체에 소속된 연구자",
    "targetSummary": "국가연구개발혁신법 제2조제3호 및 기초연구진흥법 제14조에서 정하는 대학·출연연·기업(기업부설연구소 보유) 등 연구개발기관과 소속 연구자. 반도체 분야 고경력 퇴직인력을 활용하는 기술컨설팅 과제. 전임 여부 조건은 없음."
  },
  "notFound": [],
  "confidence": "high",
  "evidenceQuotes": [
    "'26.4.~'31.12. (5년 9개월)",
    "과제기간/예산(정부출연금): '26년~'31년 / 총 72억원('26년 12억원)",
    "반도체 분야 고경력 퇴직인력을 활용하여 장비구축, 서비스 최적화, 서비스향상, 기술사업화 등 지원",
    "연구책임자의 자격 -「국가연구개발혁신법」제2조제3호에서 정하는 기관 및 단체에 소속된 연구자"
  ],
  "source": "hwp"
}
