{
  "postNo": "265518",
  "researchPeriod": { "totalText": "2026.4.1.~2030.12.31. (3+2년)", "totalMonths": 57, "byStageText": "총 3+2년(단계 구성). 1차년도 2026.4.1.~2026.12.31., 2차년도 2027.1.1.~2027.12.31., 3차년도 2028.1.1.~2028.12.31., 4차년도 2029.1.1.~2029.12.31., 5차년도 2030.1.1.~2030.12.31.", "firstYearText": "2026.4.1.~2026.12.31." },
  "funding": { "perYearPerProjectText": "당해(1차년도) 연구비 64억원(간접비 포함). 2차년도 77억원, 3차년도 84억원, 4차년도 72억원, 5차년도 56.5억원.", "totalScaleText": "'26년 64억원(당해 정부출연금); 사업기간 '26년~'30년", "numAwardsText": "선정 예정 과제 수 1개 내외(총 1개 과제 내외)" },
  "eligibility": { "employmentType": "무관/해당없음", "employmentEvidence": "연구개발기관의 자격: 「국가연구개발혁신법」제2조 제3호 및 동법 시행령 제2조에서 정하는 기관 및 단체 / 연구책임자의 자격: 「국가연구개발혁신법」제2조제3호에서 정하는 기관 및 단체에 소속된 연구자", "targetSummary": "국가연구개발혁신법상 대학·출연연·기업 등 연구개발기관과 그 소속 연구자를 대상으로 하며, 제품 양산·사업화 경험을 보유한 기관 참여가 필요한 민관협력 AI 휴머노이드 원천기술 R&D 신규과제. 전임 여부와 무관하게 기관 소속 연구자가 연구책임자 자격." },
  "notFound": [],
  "confidence": "high",
  "evidenceQuotes": [
    "총 연구기간 2026.4.1.~2030.12.31. (3+2년)",
    "1차년도 2026.4.1.~2026.12.31. 64(억원)",
    "지원 분야: 민관협력 기반 AI 휴머노이드 원천기술 고도화(R&D) 사업 총 1개 과제 내외",
    "연구개발기관의 자격 -「국가연구개발혁신법」제2조 제3호 및 동법 시행령 제2조에서 정하는 기관 및 단체",
    "참여기관 등의 형태로 제품 양산·사업화 경험을 보유한 기관 참여 필요"
  ],
  "source": "hwp"
}
